{"bookSourceGroup":"普通","bookSourceName":"书香云集💯","bookSourceUrl":"http://www.sxyj.net","checkUrl":"","enable":false,"httpUserAgent":"","ruleBookAuthor":"class.book-author.0@tag.a.0@text","ruleBookContent":"class.body@textNodes","ruleBookName":"class.book-name.0@tag.h1.0@text","ruleChapterList":"tag.ul@tag.li","ruleChapterName":"class.title.0@text","ruleChapterUrl":"class.btn-group.0@tag.a.2@href","ruleChapterUrlNext":"","ruleContentUrl":"tag.a.0@href","ruleCoverUrl":"class.book-info.0@tag.img.0@src","ruleFindUrl":"","ruleIntroduce":"class.book-summary.0@text","ruleSearchAuthor":"class.book-author.0@tag.span.0@text","ruleSearchCoverUrl":"tag.img.0@src","ruleSearchKind":"class.book-tags.0@text","ruleSearchLastChapter":"","ruleSearchList":"class.body@tag.li","ruleSearchName":"class.book-name.0@tag.a.0@text","ruleSearchNoteUrl":"class.book-name.0@tag.a.0@href","ruleSearchUrl":"http://www.sxyj.net/Book_Search.html?keyword=searchKey","serialNumber":79,"weight":0}