{"bookSourceGroup":"","bookSourceName":"掌阅[手机版][内容防盗]","bookSourceUrl":"http://m.zhangyue.com","checkUrl":"","enable":false,"httpUserAgent":"","ruleBookAuthor":"","ruleBookContent":"$class.read_c normal@html","ruleBookName":"","ruleChapterList":"class.catalog_ls@tag.li","ruleChapterName":"tag.a@text","ruleChapterUrl":"class.title@tag.a@href","ruleChapterUrlNext":"","ruleContentUrl":"tag.a@href","ruleCoverUrl":"class.side@tag.img@src","ruleFindUrl":"男频*玄幻::http://m.zhangyue.com/category/10/11?currentPage=searchPage&&男频*都 市::http://m.zhangyue.com/category/10/27?currentPage=searchPage&&男频*武 侠::http://m.zhangyue.com/category/10/19?currentPage=searchPage&&男频*仙 侠::http://m.zhangyue.com/category/10/22?currentPage=searchPage&&男频*奇 幻::http://m.zhangyue.com/category/10/16?currentPage=searchPage&&男频*校 园::http://m.zhangyue.com/category/10/39?currentPage=searchPage&&男频*历 史::http://m.zhangyue.com/category/10/42?currentPage=searchPage&&男频*军 事::http://m.zhangyue.com/category/10/50?currentPage=searchPage&&男频*游 戏::http://m.zhangyue.com/category/10/54?currentPage=searchPage&&男频*竞 技::http://m.zhangyue.com/category/10/57?currentPage=searchPage&&男频*科 幻::http://m.zhangyue.com/category/10/60?currentPage=searchPage&&女频*现代言 情::http://m.zhangyue.com/category/68/69?currentPage=searchPage&&女频*古代言 情::http://m.zhangyue.com/category/68/74?currentPage=searchPage&&女频*幻想言 情::http://m.zhangyue.com/category/68/82?currentPage=searchPage&&女频*青春校 园::http://m.zhangyue.com/category/68/86?currentPage=searchPage&&女频*同人作 品::http://m.zhangyue.com/category/68/89?currentPage=searchPage&&女频*推理悬 疑::http://m.zhangyue.com/category/68/90?currentPage=searchPage&&女频*惊悚/恐 怖::http://m.zhangyue.com/category/68/91?currentPage=searchPage&&女频*次元专 区::http://m.zhangyue.com/category/68/723?currentPage=searchPage&&男生热销榜::http://m.zhangyue.com/rank/list/19258?name=%E7%83%AD%E9%94%80%E6%A6%9C&&男生完结榜::http://m.zhangyue.com/rank/list/19265?name=%E5%AE%8C%E7%BB%93%E6%A6%9C&&男生免费榜::http://m.zhangyue.com/rank/list/19272?name=%E5%85%8D%E8%B4%B9%E6%A6%9C&&男生武道为王榜::http://m.zhangyue.com/rank/list/19267?name=%E6%AD%A6%E9%81%93%E4%B8%BA%E7%8E%8B%E6%A6%9C&&女生热销榜::http://m.zhangyue.com/rank/list/19261?name=%E7%83%AD%E9%94%80%E6%A6%9C&&女生完结榜::http://m.zhangyue.com/rank/list/19264?name=%E5%AE%8C%E7%BB%93%E6%A6%9C&&女生免费榜::http://m.zhangyue.com/rank/list/19269?name=%E5%85%8D%E8%B4%B9%E6%A6%9C&&女生灵异新书榜::http://m.zhangyue.com/rank/list/19266?name=%E7%81%B5%E5%BC%82%E6%96%B0%E4%B9%A6%E6%A6%9C","ruleIntroduce":"class.brief_intro@text","ruleSearchAuthor":"class.author@text|class.author ellipsis@text","ruleSearchCoverUrl":"tag.img@data-src|tag.img@src","ruleSearchKind":"","ruleSearchLastChapter":"","ruleSearchList":"class.section_b@tag.a|class.rank_booklist@tag.li|class.category_booklist@tag.li","ruleSearchName":"class.name ellipsis@text|tag.dt@text#-.*","ruleSearchNoteUrl":"tag.a@href|href","ruleSearchUrl":"http://m.zhangyue.com/search?keyWord=searchKey","serialNumber":630,"weight":0}