{"bookSourceGroup":"普通","bookSourceName":"英文小说","bookSourceUrl":"http://novel.tingroom.com","checkUrl":"","enable":false,"httpUserAgent":"","ruleBookAuthor":"class.writer@text#\\s+","ruleBookContent":"$tag.p@text#\\\\|$class.content HJHuaCi@text#\\\\","ruleBookName":"class.sm@text","ruleChapterList":"class.listtxt@tag.li","ruleChapterName":"text","ruleChapterUrl":"","ruleChapterUrlNext":"","ruleContentUrl":"tag.a.0@href#amp;","ruleCoverUrl":"tag.img@src","ruleFindUrl":"金典英文小说::http://novel.tingroom.com/wap/index.php?moduleid=1025&catid=1&type=2&page=searchPage&&双语小说::http://novel.tingroom.com/wap/index.php?moduleid=1025&catid=33&type=2&page=searchPage&&英文名人传记::http://novel.tingroom.com/wap/index.php?moduleid=1025&catid=32&type=2&page=searchPage&&英文励志小说::http://novel.tingroom.com/wap/index.php?moduleid=1025&catid=6&type=2&page=searchPage&&儿童英文小说::http://novel.tingroom.com/wap/index.php?moduleid=1025&catid=29&type=2&page=searchPage&&英文科幻小说::http://novel.tingroom.com/wap/index.php?moduleid=1025&catid=30&type=2&page=searchPage&&宗教英文小说::http://novel.tingroom.com/wap/index.php?moduleid=1025&catid=28&type=2&page=searchPage","ruleIntroduce":"id.infoShort@text","ruleSearchAuthor":"","ruleSearchCoverUrl":"tag.img@src","ruleSearchKind":"","ruleSearchLastChapter":"","ruleSearchList":"class.list_1","ruleSearchName":"class.name.0@text","ruleSearchNoteUrl":"class.name.0@tag.a.0@href#amp;","ruleSearchUrl":"http://novel.tingroom.com/wap/index.php?moduleid=1025&catid=1&areaid=0&type=2&kw=searchKey&page=searchPage","serialNumber":455,"weight":0}